CHANGES.txt
DEPENDENCES.txt
README.txt
TODO.txt
setup.py
src/ng/__init__.py
src/ng.app.quota.egg-info/PKG-INFO
src/ng.app.quota.egg-info/SOURCES.txt
src/ng.app.quota.egg-info/dependency_links.txt
src/ng.app.quota.egg-info/namespace_packages.txt
src/ng.app.quota.egg-info/not-zip-safe
src/ng.app.quota.egg-info/requires.txt
src/ng.app.quota.egg-info/top_level.txt
src/ng/app/__init__.py
src/ng/app/quota/__init__.py
src/ng/app/quota/configure.zcml
src/ng/app/quota/interfaces.py
src/ng/app/quota/ng.app.quota.txt
src/ng/app/quota/quota.py
src/ng/app/quota/quotaannotationadapter.py
src/ng/app/quota/quotautilityadapter.py
src/ng/app/quota/browser/__init__.py
src/ng/app/quota/browser/configure.zcml
src/ng/app/quota/browser/edit.pt
src/ng/app/quota/browser/histogram.py
src/ng/app/quota/browser/quotareindex.py
src/ng/app/quota/demo/__init__.py
src/ng/app/quota/demo/configure.zcml
src/ng/app/quota/etc/ng.app.quota-configure.zcml
src/ng/app/quota/quotahandle/__init__.py
src/ng/app/quota/quotahandle/configure.zcml
src/ng/app/quota/quotahandle/handle.py
src/ng/app/quota/quotahandle/quotaalladapter.py
src/ng/app/quota/quotahandle/quotautilities.py