Metadata-Version: 1.0
Name: ng.app.quota
Version: 1.1.0
Summary: Quota and size statistic package
Home-page: http://www.dreambot.ru/product/DreamBotZope3Releases/ng.app.quota
Author: Andrey Orlov
Author-email: dbdt@dreambot.ru
License: GPL v2.1
Platform: UNKNOWN
Classifier: Environment :: Web Environment
Classifier: Intended Audience :: Developers
Classifier: License :: OSI Approved :: GNU General Public License (GPL)
Classifier: Programming Language :: Python
Classifier: Operating System :: OS Independent
Classifier: Topic :: Internet :: WWW/HTTP
Classifier: Framework :: Zope3
